{
  "$schema": "https://raw.githubusercontent.com/spdx/spdx-spec/v2.2.1/schemas/spdx-schema.json",
  "spdxVersion": "SPDX-2.2",
  "dataLicense": "CC0-1.0",
  "SPDXID": "SPDXRef-DOCUMENT",
  "documentNamespace": "https://spdx.org/spdxdocs/boost-flyweight-x64-windows-1.86.0-3bbd07ea-e490-49b7-850d-c52e4012e1ac",
  "name": "boost-flyweight:x64-windows@1.86.0 a841bb22ad6f9c5022e4dbd9e650c78ec15a2d2f0ca3dab808446510e601e953",
  "creationInfo": {
    "creators": [
      "Tool: vcpkg-2025-01-29-a75ad067f470c19f030361064e32a2585392bee2"
    ],
    "created": "2025-04-02T22:48:15Z"
  },
  "relationships": [
    {
      "spdxElementId": "SPDXRef-port",
      "relationshipType": "GENERATES",
      "relatedSpdxElement": "SPDXRef-binary"
    },
    {
      "spdxElementId": "SPDXRef-port",
      "relationshipType": "CONTAINS",
      "relatedSpdxElement": "SPDXRef-file-0"
    },
    {
      "spdxElementId": "SPDXRef-port",
      "relationshipType": "CONTAINS",
      "relatedSpdxElement": "SPDXRef-file-1"
    },
    {
      "spdxElementId": "SPDXRef-binary",
      "relationshipType": "GENERATED_FROM",
      "relatedSpdxElement": "SPDXRef-port"
    },
    {
      "spdxElementId": "SPDXRef-file-0",
      "relationshipType": "CONTAINED_BY",
      "relatedSpdxElement": "SPDXRef-port"
    },
    {
      "spdxElementId": "SPDXRef-file-1",
      "relationshipType": "CONTAINED_BY",
      "relatedSpdxElement": "SPDXRef-port"
    }
  ],
  "packages": [
    {
      "name": "boost-flyweight",
      "SPDXID": "SPDXRef-port",
      "versionInfo": "1.86.0",
      "downloadLocation": "git+https://github.com/microsoft/vcpkg@b009b7937daa96c41f1afbba2693f507471e47d9",
      "homepage": "https://www.boost.org/libs/flyweight",
      "licenseConcluded": "BSL-1.0",
      "licenseDeclared": "NOASSERTION",
      "copyrightText": "NOASSERTION",
      "description": "Boost flyweight module",
      "comment": "This is the port (recipe) consumed by vcpkg."
    },
    {
      "name": "boost-flyweight:x64-windows",
      "SPDXID": "SPDXRef-binary",
      "versionInfo": "a841bb22ad6f9c5022e4dbd9e650c78ec15a2d2f0ca3dab808446510e601e953",
      "downloadLocation": "NONE",
      "licenseConcluded": "BSL-1.0",
      "licenseDeclared": "NOASSERTION",
      "copyrightText": "NOASSERTION",
      "comment": "This is a binary package built by vcpkg."
    },
    {
      "SPDXID": "SPDXRef-resource-0",
      "name": "boostorg/flyweight",
      "downloadLocation": "git+https://github.com/boostorg/flyweight@boost-1.86.0",
      "licenseConcluded": "NOASSERTION",
      "licenseDeclared": "NOASSERTION",
      "copyrightText": "NOASSERTION",
      "checksums": [
        {
          "algorithm": "SHA512",
          "checksumValue": "dc5862df3f1f1b8d8704175952690011dd02e01cd396318b24da4d52e9b5c12da27903128a6003439b92934ce4fb3341b42972152793d17768a04acedcf0bde7"
        }
      ]
    }
  ],
  "files": [
    {
      "fileName": "./C:/Users/walte/AppData/Local/vcpkg/registries/git-trees/b009b7937daa96c41f1afbba2693f507471e47d9/portfile.cmake",
      "SPDXID": "SPDXRef-file-0",
      "checksums": [
        {
          "algorithm": "SHA256",
          "checksumValue": "e4caa9c392ba5dc99be3b1d50062a691594f4863db57dae7f9345458f2acf571"
        }
      ],
      "licenseConcluded": "NOASSERTION",
      "copyrightText": "NOASSERTION"
    },
    {
      "fileName": "./C:/Users/walte/AppData/Local/vcpkg/registries/git-trees/b009b7937daa96c41f1afbba2693f507471e47d9/vcpkg.json",
      "SPDXID": "SPDXRef-file-1",
      "checksums": [
        {
          "algorithm": "SHA256",
          "checksumValue": "4f056fbc7327b7f9238d0e90c41ed1d46fda687e9ae1c6524f384a01dfafa64f"
        }
      ],
      "licenseConcluded": "NOASSERTION",
      "copyrightText": "NOASSERTION"
    }
  ]
}
